iservice/__init__.py
iservice/inject.py
iservice/mypy_check.py
iservice/mypy_check_2.py
iservice/py.typed
iservice/service.py
iservice-0.2.3.dist-info/METADATA
iservice-0.2.3.dist-info/WHEEL
iservice-0.2.3.dist-info/licenses/AUTHORS.rst
iservice-0.2.3.dist-info/licenses/LICENCE
iservice-0.2.3.dist-info/RECORD
