Metadata-Version: 2.1
Name: iservice
Version: 0.2.3
Summary: Service injector to create multiple version of a service with ease and safety.
Project-URL: Bug Tracker, https://lab.frogg.it/dorianturba/iservice
Project-URL: Homepage, https://lab.frogg.it/dorianturba/iservice
Author-email: Dorian Turba <contact.2xv8p@8shield.net>
License-File: AUTHORS.rst
License-File: LICENCE
Classifier: Development Status :: 3 - Alpha
Classifier: License :: OSI Approved :: MIT License
Classifier: Operating System :: OS Independent
Classifier: Programming Language :: Python :: 3
Classifier: Programming Language :: Python :: 3.10
Classifier: Programming Language :: Python :: 3.11
Classifier: Programming Language :: Python :: 3.12
Classifier: Typing :: Typed
Requires-Python: >=3.10
Provides-Extra: all
Requires-Dist: iservice[manage]; extra == 'all'
Requires-Dist: iservice[quality]; extra == 'all'
Requires-Dist: iservice[test]; extra == 'all'
Provides-Extra: manage
Requires-Dist: bump-my-version; extra == 'manage'
Provides-Extra: quality
Requires-Dist: black; extra == 'quality'
Requires-Dist: flake8; extra == 'quality'
Requires-Dist: isort; extra == 'quality'
Requires-Dist: mypy; extra == 'quality'
Requires-Dist: pre-commit; extra == 'quality'
Provides-Extra: test
Requires-Dist: coverage; extra == 'test'
Requires-Dist: pytest; extra == 'test'
